{
  "meta": {
    "title": "Get a Quote - Contact Us",
    "description": "Get in touch with {fullName} for fast, reliable plumbing solutions. Request a quote, schedule service, or ask questions. Call {phone}!"
  },
  "sections": [
    {
      "component": "HeroSection",
      "props": {
        "variant": "subpage",
        "title": "Contact Us",
        "subtitle": "Get in touch for fast, reliable plumbing solutions in {city} and surrounding areas. We're here to help with all your plumbing needs, big or small.",
        "buttonText": "SCHEDULE SERVICE",
        "buttonHref": "#contact-form",
        "image": "/images/photos/unsplash-1558618666-fcd25c85cd64-w1000.jpg",
        "trustIndicators": [
          "Fast Response Times",
          "Free Estimates",
          "24/7 Emergency Service"
        ]
      }
    },
    {
      "component": "ContactFormSection",
      "props": {
        "title": "Get in Touch with {fullName}",
        "description": "Fill out the form, and a member of our team will get back to you promptly. Whether you're looking for a quick repair, a detailed quote, or general advice, we've got you covered.",
        "image": "/images/photos/unsplash-1621905251189-08b45d6a269e-w800.jpg",
        "phone": "{phone}",
        "email": "{email}",
        "address": "{city}, {state}",
        "serviceOptions": [
          "Residential Plumbing",
          "Commercial Plumbing",
          "Emergency Service",
          "Drain Cleaning",
          "Water Heater",
          "Maintenance",
          "Other"
        ],
        "planOptions": [
          "Yes",
          "No",
          "Not Sure"
        ]
      }
    },
    {
      "component": "CTAStrip",
      "props": {
        "buttonText": "SCHEDULE NOW",
        "buttonHref": "tel:{phoneRaw}",
        "phoneLabel": "Call or Text for Great Service",
        "phone": "{phone}",
        "borderColor": "#7dd3fc",
        "features": [
          {
            "icon": "siren",
            "text": "24/7 Emergency Service"
          },
          {
            "icon": "award",
            "text": "Experienced and Certified Technician"
          }
        ]
      }
    },
    {
      "component": "ServiceAreaSection",
      "props": {
        "title": "Expert Plumbing Services in {city} and Surrounding Areas",
        "description": "Looking for reliable plumbing services in {city}? We provide expert residential and commercial solutions across the city. Whether you need <a href='/residential/leak/detection'><strong>leak detection</strong></a>, <a href='/residential/drain/cleaning'><strong>drain cleaning</strong></a>, <a href='/residential/water-heaters/standard'><strong>water heater</strong></a> repairs, or advanced pipe relining, our licensed team serves your area with speed, skill, and care.",
        "areas": [
          "Santa Monica",
          "Pasadena",
          "Glendale",
          "Downtown {city}",
          "Hollywood",
          "Beverly Hills",
          "Venice",
          "Westwood",
          "Culver City",
          "San Fernando Valley",
          "Sherman Oaks",
          "Encino",
          "Burbank",
          "Torrance",
          "Long Beach",
          "Inglewood",
          "El Segundo",
          "Brentwood",
          "Silver Lake",
          "Echo Park",
          "Hancock Park",
          "Marina del Rey",
          "Manhattan Beach"
        ],
        "mapAddress": "{city}, {state}"
      }
    }
  ]
}
